<?xml version="1.0" encoding="UTF-8"?>
<Data>
    <DialogConfig>
        <name>suomen</name>
        <prefab>WindowDialog</prefab>
        <defaultSpeaker>时光</defaultSpeaker>
        <textReadInterval>0.08</textReadInterval>
        <content>
            <li>
                <speaker>时光</speaker>
                <text>打开了！</text>
            </li>
        </content>
    </DialogConfig>

	<DialogConfig>
		<name>jiepaiqi</name>
		<prefab>WindowDialog</prefab>
		<defaultSpeaker>时光</defaultSpeaker>
		<textReadInterval>0.08</textReadInterval>
		<content>
			<li>
				<speaker>时光</speaker>
				<text>没想到过了这么久还能用。</text>
			</li>
		</content>
	</DialogConfig>

	<DialogConfig>
		<name>yugang</name>
		<prefab>WindowDialog</prefab>
		<defaultSpeaker>时光</defaultSpeaker>
		<textReadInterval>0.08</textReadInterval>
		<content>
			<li>
				<speaker>时光</speaker>
				<text>上一次泡热水澡是什么时候来着？</text>
			</li>
		</content>
	</DialogConfig>

	<DialogConfig>
		<name>yuandeng</name>
		<prefab>WindowDialog</prefab>
		<defaultSpeaker>时光</defaultSpeaker>
		<textReadInterval>0.08</textReadInterval>
		<content>
			<li>
				<speaker>时光</speaker>
				<text>以前的灶台有这么矮吗？</text>
			</li>
		</content>
	</DialogConfig>

	<DialogConfig>
		<name>pujia</name>
		<prefab>WindowDialog</prefab>
		<defaultSpeaker>时光</defaultSpeaker>
		<textReadInterval>0.08</textReadInterval>
		<content>
			<li>
				<speaker>时光</speaker>
				<text>早知道砸完要我自己买，我就不砸了！</text>
			</li>
		</content>
	</DialogConfig>

	<DialogConfig>
		<name>xiangkuang</name>
		<prefab>WindowDialog</prefab>
		<defaultSpeaker>时光</defaultSpeaker>
		<textReadInterval>0.08</textReadInterval>
		<content>
			<li>
				<speaker>时光</speaker>
				<text>如今的我，还能像以前一样“固执”下去吗？</text>
			</li>
		</content>
	</DialogConfig>

	<DialogConfig>
		<name>gangqin</name>
		<prefab>WindowDialog</prefab>
		<defaultSpeaker>时光</defaultSpeaker>
		<textReadInterval>0.08</textReadInterval>
		<content>
			<li>
				<speaker>时光</speaker>
				<text>。。。。。。</text>
			</li>
		</content>
	</DialogConfig>

	<DialogConfig>
		<name>anniu</name>
		<prefab>WindowDialog</prefab>
		<defaultSpeaker>时光</defaultSpeaker>
		<textReadInterval>0.08</textReadInterval>
		<content>
			<li>
				<speaker>时光</speaker>
				<text>我记得...按钮是在那面？</text>
			</li>
		</content>
	</DialogConfig>

	<DialogConfig>
		<name>kuaidi</name>
		<prefab>WindowDialog</prefab>
		<defaultSpeaker>时光</defaultSpeaker>
		<textReadInterval>0.08</textReadInterval>
		<content>
			<li>
				<speaker>时光</speaker>
				<text>这位小哥不好意思，走路花了些时间，可以麻烦你帮我把外卖拿进去吗？</text>
			</li>
		</content>
	</DialogConfig>
</Data>